libgenapi/__init__.py
libgenapi/libgenapi.py
libgenapi-1.2.0.dist-info/DESCRIPTION.rst
libgenapi-1.2.0.dist-info/METADATA
libgenapi-1.2.0.dist-info/RECORD
libgenapi-1.2.0.dist-info/WHEEL
libgenapi-1.2.0.dist-info/metadata.json
libgenapi-1.2.0.dist-info/top_level.txt
