Metadata-Version: 2.0
Name: libgenapi
Version: 1.2.0
Summary: Library to search on Library genesis
Home-page: https://github.com/mmarquezs/libgen-python-api/
Author: Marc Marquez Santamaria
Author-email: mmsa1994@gmail.com
License: MIT
Keywords: libgen search crawl development
Platform: UNKNOWN
Classifier: Development Status :: 3 - Alpha
Classifier: Intended Audience :: Developers
Classifier: Topic :: Software Development :: Libraries
Classifier: License :: OSI Approved :: MIT License
Classifier: Programming Language :: Python :: 3
Classifier: Programming Language :: Python :: 3.2
Classifier: Programming Language :: Python :: 3.3
Classifier: Programming Language :: Python :: 3.4
Classifier: Programming Language :: Python :: 3.5
Requires-Dist: grab
